smartenvx/__init__.py
smartenvx/core.py
smartenvx/exceptions.py
smartenvx/utils.py
smartenvx-0.1.0.dist-info/licenses/LICENSE
smartenvx-0.1.0.dist-info/METADATA
smartenvx-0.1.0.dist-info/WHEEL
smartenvx-0.1.0.dist-info/top_level.txt
smartenvx-0.1.0.dist-info/RECORD
