Metadata-Version: 2.4
Name: smartenvx
Version: 0.1.0
Summary: Smart .env loader with validation, fallback values, and secure masking.
Author-email: Adediran Ayomide Mathew <ayomideadediran45@gmail.com>
License: MIT
Project-URL: Homepage, https://github.com/Ay-developerweb/smartenvx
Project-URL: Bug Tracker, https://github.com/Ay-developerweb/smartenvx/issues
Requires-Python: >=3.6
License-File: LICENSE
Requires-Dist: python-dotenv
Dynamic: license-file
